cogents/__init__.py
cogents/agents/__init__.py
cogents/agents/askura_agent/README.md
cogents/agents/askura_agent/__init__.py
cogents/agents/askura_agent/askura_agent.py
cogents/agents/askura_agent/conversation.py
cogents/agents/askura_agent/extractor.py
cogents/agents/askura_agent/memory.py
cogents/agents/askura_agent/models.py
cogents/agents/askura_agent/prompts.py
cogents/agents/askura_agent/reflection.py
cogents/agents/askura_agent/summarizer.py
cogents/agents/cogito_agent/__init__.py
cogents/agents/cogito_agent/gws/__init__.py
cogents/agents/cogito_agent/sensory/__init__.py
cogents/agents/mem_agent/__init__.py
cogents/agents/seekra_agent/__init__.py
cogents/agents/seekra_agent/configuration.py
cogents/agents/seekra_agent/prompts.py
cogents/agents/seekra_agent/researcher.py
cogents/agents/seekra_agent/schemas.py
cogents/agents/seekra_agent/state.py
cogents/base/__init__.py
cogents/base/base_agent.py
cogents/base/base_search.py
cogents/base/base_vectorstore.py
cogents/base/base_websurfer.py
cogents/base/consts.py
cogents/base/llm/__init__.py
cogents/base/llm/base.py
cogents/base/llm/litellm.py
cogents/base/llm/llamacpp.py
cogents/base/llm/ollama.py
cogents/base/llm/openai.py
cogents/base/llm/openrouter.py
cogents/base/logging.py
cogents/base/msgbus/README.md
cogents/base/msgbus/__init__.py
cogents/base/msgbus/base.py
cogents/base/routing/__init__.py
cogents/base/routing/base.py
cogents/base/routing/router.py
cogents/base/routing/strategies/__init__.py
cogents/base/routing/strategies/dynamic_complexity.py
cogents/base/routing/strategies/self_assessment.py
cogents/base/routing/types.py
cogents/base/tracing/__init__.py
cogents/base/tracing/langgraph_hooks.py
cogents/base/tracing/opik_tracing.py
cogents/base/tracing/token_tracker.py
cogents/base/typing_compat.py
cogents/base/utils.py
cogents/goalith/conflict/conflict.py
cogents/goalith/conflict/detector.py
cogents/goalith/decomposer/__init__.py
cogents/goalith/decomposer/base.py
cogents-0.0.18.dist-info/LICENSE
cogents-0.0.18.dist-info/METADATA
cogents-0.0.18.dist-info/WHEEL
cogents-0.0.18.dist-info/RECORD
