Metadata-Version: 2.3
Name: cogents
Version: 0.0.18
Summary: Towards a cognitive agentic framework
License: MIT
Keywords: agents,multi-agent system,cognition,artificial intelligence
Author: Xiaming Chen
Author-email: chenxm35@gmail.com
Maintainer: Xiaming Chen
Maintainer-email: chenxm35@gmail.com
Requires-Python: >=3.11,<4.0
Classifier: Development Status :: 3 - Alpha
Classifier: Intended Audience :: Developers
Classifier: License :: OSI Approved :: MIT License
Classifier: Operating System :: OS Independent
Classifier: Programming Language :: Python :: 3
Classifier: Programming Language :: Python :: 3.11
Classifier: Programming Language :: Python :: 3.12
Classifier: Programming Language :: Python :: 3.13
Classifier: Topic :: Software Development :: Libraries :: Python Modules
Requires-Dist: aiohttp (>=3.9.0,<4.0.0)
Requires-Dist: anyio (>=4.10.0,<5.0.0)
Requires-Dist: bubus (>=1.5.6,<2.0.0)
Requires-Dist: colorlog (>=6.8.0,<7.0.0)
Requires-Dist: deprecated (>=1.2.18,<2.0.0)
Requires-Dist: google-genai (>=1.5.0,<2.0.0)
Requires-Dist: httpx (>=0.28.1,<0.29.0)
Requires-Dist: huggingface-hub (>=0.34.4,<0.35.0)
Requires-Dist: instructor (>=1.10.0,<2.0.0)
Requires-Dist: langchain-core (>=0.3.72,<0.4.0)
Requires-Dist: langchain-ollama (>=0.2.0,<0.3.0)
Requires-Dist: langchain-tavily (>=0.2.11,<0.3.0)
Requires-Dist: langchain-text-splitters (>=0.3.0,<0.4.0)
Requires-Dist: langgraph (>=0.5.4,<0.6.0)
Requires-Dist: litellm (>=1.0.0,<2.0.0)
Requires-Dist: llama-cpp-python (>=0.3.16,<0.4.0)
Requires-Dist: mcp (>=1.0.0,<2.0.0)
Requires-Dist: networkx (>=3.5,<4.0)
Requires-Dist: ollama (>=0.5.3,<0.6.0)
Requires-Dist: openai (>=1.0.0,<2.0.0)
Requires-Dist: psutil (>=7.0.0,<8.0.0)
Requires-Dist: pydantic (>=2.0.0,<3.0.0)
Requires-Dist: python-dotenv (>=1.1.1,<2.0.0)
Requires-Dist: requests (>=2.31.0,<3.0.0)
Requires-Dist: typing-extensions (>=4.8.0,<5.0.0)
Project-URL: Documentation, https://cogents.readthedocs.io/
Project-URL: Homepage, https://github.com/caesar0301/cogents
Project-URL: Repository, https://github.com/caesar0301/cogents
